osmcha/__init__.py
osmcha/changeset.py
osmcha/suspect_words.yaml
osmcha/warnings.py
osmcha/scripts/__init__.py
osmcha/scripts/cli.py
osmcha-0.9.2.dist-info/LICENSE
osmcha-0.9.2.dist-info/METADATA
osmcha-0.9.2.dist-info/WHEEL
osmcha-0.9.2.dist-info/entry_points.txt
osmcha-0.9.2.dist-info/top_level.txt
osmcha-0.9.2.dist-info/RECORD
