Metadata-Version: 2.1
Name: osmcha
Version: 0.9.2
Summary: Python package to detect suspicious OpenStreetMap changesets
Home-page: https://github.com/willemarcel/osmcha
Author: Wille Marcel
Author-email: wille.yyz@gmail.com
License: GPLv3+
Keywords: openstreetmap,osm,QA,gis
Platform: UNKNOWN
Classifier: Programming Language :: Python
Classifier: Programming Language :: Python :: 2
Classifier: Programming Language :: Python :: 3
Classifier: License :: OSI Approved :: GNU General Public License v3 or later (GPLv3+)
Classifier: Topic :: Scientific/Engineering :: GIS
Classifier: Topic :: Utilities
License-File: LICENSE
Requires-Dist: click
Requires-Dist: requests
Requires-Dist: shapely
Requires-Dist: python-dateutil
Requires-Dist: PyYAML
Provides-Extra: test
Requires-Dist: pytest; extra == "test"
